bopy/__init__.py
bopy/core/__init__.py
bopy/core/core.py
bopy/helpers/__init__.py
bopy/helpers/ezpadova/LICENSE
bopy/helpers/ezpadova/__init__.py
bopy/helpers/ezpadova/cmd.py
bopy/helpers/ezpadova/isochrone_grid.py
bopy/helpers/ezpadova/isochrone_interp.py
bopy/helpers/ezpadova/simpletable.py
bopy/imagetools/__init__.py
bopy/imagetools/image.py
bopy/imagetools/random_dots.py
bopy/mcmctools/__init__.py
bopy/mcmctools/emcee_try_20140704.py
bopy/mcmctools/emceetools.py
bopy/obstools/__init__.py
bopy/obstools/finder_chart.py
bopy/obstools/Xinglong216HRS/__init__.py
bopy/obstools/Xinglong216HRS/obslog.py
bopy/obstools/Xinglong216HRS/py_wspectext.py
bopy/scratch/__init__.py
bopy/scratch/nntest.py
bopy/spec/__init__.py
bopy/spec/continuum_normalization.py
bopy/spec/convolution.py
bopy/spec/dataset.py
bopy/spec/echelle.py
bopy/spec/find_continuum_pixels.py
bopy/spec/lamost.py
bopy/spec/line_indices.py
bopy/spec/pollux.py
bopy/spec/radial_velocity.py
bopy/spec/read_spectrum.py
bopy/spec/spec.py
bopy/spec/spec_quick_view.py
bopy-0.4.0.dist-info/METADATA
bopy-0.4.0.dist-info/RECORD
bopy-0.4.0.dist-info/WHEEL
bopy-0.4.0.dist-info/top_level.txt
