Metadata-Version: 2.1
Name: bopy
Version: 0.4.0
Summary: Bo Zhang (@NAOC)s python package.
Home-page: http://github.com/hypergravity/bopy
Author: Bo Zhang
Author-email: bozhang@nao.cas.cn
License: New BSD
Platform: UNKNOWN
Classifier: Development Status :: 5 - Production/Stable
Classifier: Intended Audience :: Science/Research
Classifier: License :: OSI Approved :: MIT License
Classifier: Operating System :: OS Independent
Classifier: Programming Language :: Python :: 3.7
Classifier: Topic :: Scientific/Engineering :: Physics
Classifier: Topic :: Scientific/Engineering :: Astronomy
Requires: numpy
Requires: scipy
Requires: matplotlib
Requires: astropy
Requires: emcee
Requires: joblib
